.gitignore
LICENSE.txt
README.md
setup.py
nmigen_boards/__init__.py
nmigen_boards/arty_a7.py
nmigen_boards/atlys.py
nmigen_boards/blackice.py
nmigen_boards/blackice_ii.py
nmigen_boards/de0.py
nmigen_boards/de0_cv.py
nmigen_boards/de10_nano.py
nmigen_boards/ecp5_5g_evn.py
nmigen_boards/fomu_hacker.py
nmigen_boards/ice40_hx1k_blink_evn.py
nmigen_boards/ice40_hx8k_b_evn.py
nmigen_boards/icebreaker.py
nmigen_boards/icestick.py
nmigen_boards/kc705.py
nmigen_boards/kcu105.py
nmigen_boards/mercury.py
nmigen_boards/mister.py
nmigen_boards/numato_mimas.py
nmigen_boards/sk_xc6slx9.py
nmigen_boards/tinyfpga_ax1.py
nmigen_boards/tinyfpga_ax2.py
nmigen_boards/tinyfpga_bx.py
nmigen_boards/versa_ecp5.py
nmigen_boards/versa_ecp5_5g.py
nmigen_boards/zturn_lite_z007s.py
nmigen_boards/zturn_lite_z010.py
nmigen_boards.egg-info/PKG-INFO
nmigen_boards.egg-info/SOURCES.txt
nmigen_boards.egg-info/dependency_links.txt
nmigen_boards.egg-info/requires.txt
nmigen_boards.egg-info/top_level.txt
nmigen_boards/extensions/__init__.py
nmigen_boards/extensions/pmod.py
nmigen_boards/resources/__init__.py
nmigen_boards/resources/display.py
nmigen_boards/resources/interface.py
nmigen_boards/resources/memory.py
nmigen_boards/resources/user.py
nmigen_boards/test/__init__.py
nmigen_boards/test/blinky.py