Metadata-Version: 1.0
Name: nmigen-boards
Version: 0.0
Summary: Board and connector definitions for nMigen
Home-page: UNKNOWN
Author: whitequark
Author-email: whitequark@whitequark.org
License: BSD
Project-URL: Source Code, https://github.com/m-labs/nmigen-boards
Project-URL: Bug Tracker, https://github.com/m-labs/nmigen-boards/issues
Platform: UNKNOWN
